gps2gtfs/__init__.py
gps2gtfs/data_field/__init__.py
gps2gtfs/data_field/im_field.py
gps2gtfs/data_field/input_field.py
gps2gtfs/data_field/output_field.py
gps2gtfs/load_data/__init__.py
gps2gtfs/load_data/load_from_csv.py
gps2gtfs/pipeline/__init__.py
gps2gtfs/pipeline/trip.py
gps2gtfs/pipeline/trip_stop.py
gps2gtfs/preprocessing/__init__.py
gps2gtfs/preprocessing/data_cleaner.py
gps2gtfs/reporting/__init__.py
gps2gtfs/stop/__init__.py
gps2gtfs/stop/data_preparator.py
gps2gtfs/stop/feature_extractor.py
gps2gtfs/stop/stop_extractor.py
gps2gtfs/trip/__init__.py
gps2gtfs/trip/feature_extractor.py
gps2gtfs/trip/trip_extractor.py
gps2gtfs/utility/__init__.py
gps2gtfs/utility/data_io_converter.py
gps2gtfs/utility/logger.py
gps2gtfs-0.1.0.dist-info/LICENSE
gps2gtfs-0.1.0.dist-info/METADATA
gps2gtfs-0.1.0.dist-info/WHEEL
gps2gtfs-0.1.0.dist-info/top_level.txt
gps2gtfs-0.1.0.dist-info/RECORD
