Metadata-Version: 2.1
Name: gps2gtfs
Version: 0.1.0
Summary: A Python package to process raw GPS data of public transit and transform to GTFS format.
Home-page: https://github.com/aaivu/gps2gtfs
Author: Aaivu
Author-email: helloaaivu@gmail.com
License: MIT
Project-URL: Homepage, https://github.com/aaivu/gps2gtfs
Project-URL: Source, https://github.com/aaivu/gps2gtfs
Project-URL: Download, https://pypi.org/project/gps2gtfs/
Project-URL: Documentation, https://github.com/aaivu/gps2gtfs/blob/master/PACKAGE_DESCRIPTION.md
Project-URL: Bug Tracker, https://github.com/aaivu/gps2gtfs/issues
Keywords: GTFS,GPS,Travel Time,Public Transit,Heterogeneous Traffic Condition,ITS
Platform: UNKNOWN
Classifier: Development Status :: 3 - Alpha
Classifier: Intended Audience :: Developers
Classifier: Intended Audience :: Science/Research
Classifier: Programming Language :: Python :: 3 :: Only
Classifier: Programming Language :: Python :: 3.6
Classifier: Programming Language :: Python :: 3.7
Classifier: Programming Language :: Python :: 3.8
Classifier: Programming Language :: Python :: 3.9
Classifier: Programming Language :: Python :: 3.10
Classifier: Programming Language :: Python :: 3.11
Classifier: License :: OSI Approved :: MIT License
Classifier: Operating System :: OS Independent
Classifier: Topic :: Scientific/Engineering
Classifier: Topic :: Software Development
Requires-Python: >=3.6
License-File: LICENSE
Requires-Dist: pandas
Requires-Dist: geopandas
Requires-Dist: numpy
